ecmind_purple_utils/__init__.py
ecmind_purple_utils/utils.py
ecmind_purple_utils-0.0.4.dist-info/LICENSE
ecmind_purple_utils-0.0.4.dist-info/METADATA
ecmind_purple_utils-0.0.4.dist-info/WHEEL
ecmind_purple_utils-0.0.4.dist-info/top_level.txt
ecmind_purple_utils-0.0.4.dist-info/RECORD
