Metadata-Version: 2.1
Name: ecmind-purple-utils
Version: 0.0.4
Summary: Helper for red and blue
Home-page: https://gitlab.ecmind.ch/open/ecmind_purple_utils
Author: Ulrich Wohlfeil; Roland Koller
Author-email: info@ecmind.ch
Classifier: Programming Language :: Python :: 3
Classifier: License :: OSI Approved :: MIT License
Classifier: Operating System :: OS Independent
Requires-Python: >=3.9
License-File: LICENSE
